{  	
  "codSecaoLivro": "250",
  "texto": "\t\t\t\tO vaso cai ao chão, mas não quebra, embora apareçam rachaduras por toda parte.\n\n\t\t\t\tVocê começa a sentir uma vibração e então, nota que há rachaduras que surgem por toda parte na varanda e nos lados da cabana.\n\n\t\t\t\tA vibração fica mais forte - todo o seu corpo começa a tremer, e sua cabeça dá a sensação de estar prestes a explodir.\n\n\t\t\t\tVocê perde 2 pontos de ENERGIA.",
  "enderecoAudio":"audio/secao_250.mp3",
  "proximasSecoes": [
    {	  
      "textoOpcao": "Continue.",
      "codProximaSecao": "82"
    }
  ]
}