{  	
  "codSecaoLivro": "384",
  "texto": "\t\t\t\tÀ sua frente, no mato, você ouve um gemido baixo. Você olha para cima e vê os abutres pacientemente esperando no alto.\n\n\t\t\t\tAlguns passos adiante, você se depara com a visão horrível de um homem imenso, com músculos que parecem de ferro, preso ao chão.\n\n\t\t\t\tO homem está muitíssimo ferido pela exposição ao sol. Seu rosto e peito mostram os sinais sangrentos de torturas cruéis.\n\n\t\t\t\tSeus algozes provavelmente não conseguiram dele as informações que queriam, pois ele é um BÁRBARO!",
  "enderecoImagem": "imagens/secao/secao_384.png",
  "enderecoAudio":"audio/secao_384.mp3",
  "proximasSecoes": [
    {	  
      "textoOpcao": "Você deseja libertá-lo?",
      "codProximaSecao": "128"
    },
	{	  
      "textoOpcao": "Deixá-lo na sua agonia e voltar à trilha para seguir para o norte?",
      "codProximaSecao": "394"
    }
  ]
}